[{
		"id": 40,
		"title": "Rika",
		"year": "July 2022",
		"image": "3f",
		"sport": "Yoga",
		"january": 1,
		"february": 1,
		"march": 1,
		"april": 1,
		"may": 1,
		"june": 1,
		"july": 1,
		"august": 0,
		"september": 0,
		"october": 0,
		"november": 0,
		"december": 0,
		"created_at": "✔️",
		"updated_at": "D5-pool",
		"userid": 0
	},

	{
		"id": 41,
		"title": "Eva",
		"year": "",
		"image": "4m",
		"sport": "Yoga",
		"january": 1,
		"february": 1,
		"march": 1,
		"april": 1,
		"may": 1,
		"june": 1,
		"july": 1,
		"august": 0,
		"september": 0,
		"october": 0,
		"november": 0,
		"december": 0,
		"created_at": "✔️",
		"updated_at": "",
		"userid": 2
	},

	{
		"id": 42,
		"title": "Jen",
		"year": "",
		"image": "3f",
		"sport": "Yoga",
		"january": 1,
		"february": 1,
		"march": 1,
		"april": 1,
		"may": 1,
		"june": 1,
		"july": 1,
		"august": 0,
		"september": 0,
		"october": 0,
		"november": 0,
		"december": 0,
		"created_at": "✔️",
		"updated_at": "",
		"userid": 2
	},
	{
		"id": 43,
		"title": "Ommy",
		"year": "",
		"image": "3f",
		"sport": "Yoga",
		"january": 1,
		"february": 1,
		"march": 1,
		"april": 1,
		"may": 1,
		"june": 1,
		"july": 1,
		"august": 0,
		"september": 0,
		"october": 0,
		"november": 0,
		"december": 0,
		"created_at": "✔️",
		"updated_at": "",
		"userid": 2
	},
 {
		"id": 44,
		"title": "Liam",
		"year": "",
		"image": "4m",
		"sport": "Soccer",
		"january": 1,
		"february": 1,
		"march": 1,
		"april": 1,
		"may": 1,
		"june": 1,
		"july": 1,
		"august": 0,
		"september": 0,
		"october": 0,
		"november": 0,
		"december": 0,
		"created_at": "✔️",
		"updated_at": "",
		"userid": 2
	},
	{
		"id": 30,
		"title": "Nima",
		"year": "June 2022",
		"image": "3f",
		"sport": "Yoga",
		"january": 1,
		"february": 1,
		"march": 1,
		"april": 1,
		"may": 1,
		"june": 1,
		"july": 1,
		"august": 0,
		"september": 0,
		"october": 0,
		"november": 0,
		"december": 0,
		"created_at": "✔️",
		"updated_at": "D5-pool",
		"userid": 0
	},

	{
		"id": 31,
		"title": "Zoran",
		"year": "",
		"image": "4m",
		"sport": "Yoga",
		"january": 1,
		"february": 1,
		"march": 1,
		"april": 1,
		"may": 1,
		"june": 1,
		"july": 1,
		"august": 0,
		"september": 0,
		"october": 0,
		"november": 0,
		"december": 0,
		"created_at": "✔️",
		"updated_at": "",
		"userid": 2
	},

	{
		"id": 32,
		"title": "Jen",
		"year": "",
		"image": "3f",
		"sport": "Yoga",
		"january": 1,
		"february": 1,
		"march": 1,
		"april": 1,
		"may": 1,
		"june": 1,
		"july": 1,
		"august": 0,
		"september": 0,
		"october": 0,
		"november": 0,
		"december": 0,
		"created_at": "✔️",
		"updated_at": "",
		"userid": 2
	},
	{
		"id": 33,
		"title": "Liam",
		"year": "",
		"image": "4m",
		"sport": "Soccer",
		"january": 1,
		"february": 1,
		"march": 1,
		"april": 1,
		"may": 1,
		"june": 1,
		"july": 1,
		"august": 0,
		"september": 0,
		"october": 0,
		"november": 0,
		"december": 0,
		"created_at": "✔️",
		"updated_at": "",
		"userid": 2
	},

	{
		"id": 20,
		"title": "Zoe",
		"year": "May 2022",
		"image": "3f",
		"sport": "Yoga",
		"january": 1,
		"february": 1,
		"march": 1,
		"april": 1,
		"may": 1,
		"june": 1,
		"july": 1,
		"august": 0,
		"september": 0,
		"october": 0,
		"november": 0,
		"december": 0,
		"created_at": "✔️",
		"updated_at": "D5-pool",
		"userid": 0
	},
	{
		"id": 21,
		"title": "Nima",
		"year": "",
		"image": "3f",
		"sport": "Yoga",
		"january": 1,
		"february": 1,
		"march": 1,
		"april": 1,
		"may": 1,
		"june": 1,
		"july": 1,
		"august": 0,
		"september": 0,
		"october": 0,
		"november": 0,
		"december": 0,
		"created_at": "✔️",
		"updated_at": "D5-pool",
		"userid": 0
	}


]
